{
    "filename": "corner_ch5_tolive_14.sgf",
    "rawsgf": "(;CA[UTF-8]C[\u548c\u91d1\u6ac3\u89d2\u6709\u95dc\u806f\u7684\u5f62\u72c0\u3002]AP[MultiGo:4.2.1]SZ[19]GN[\u9ed1\u5148\u6d3b]MULTIGOGM[1]AB[dc][db][cd][ce]AW[bf][cf][df][ch][dd][ed][ec][eb][hc](;B[bb]N[\u6b63\u89e3];W[bd];B[be];W[ae];B[bc];W[ad];B[ac];W[af];B[cc];W[ca];B[da];W[ba];B[aa];W[ab];B[cb]C[\u8139\u726f\u725b])(;B[bc]N[\u5931\u6557\u57161](;W[cb](;B[ca];W[bb];B[ab];W[ba];B[da];W[ad]C[\u9ed1\u68cb\u6de8\u6b7b\u3002\u767d\u68cb\u7684\u624b\u6cd5\u985e\u4f3c\u7b2c12\u578b\u7684\u7684\u6b63\u89e32\u3002])(;B[cc]MN[3]N[\u8b8a\u5316\u57161](;W[ba](;B[bb];W[da]C[\u9ed1\u7684\u5148\u624b\u52ab\u3002])(;B[da]MN[5]N[\u9ed1\u4e0d\u884c];W[ad]C[\u6bba\u68cb\u7684\u597d\u624b\u3002];B[bb];W[ac](;B[ca];W[ab]C[\u9ed1\u68cb\u53ea\u6709\u4e00\u96bb\u773c\u3002])(;B[ab]MN[9]N[\u8b8a\u5316\u5716];W[ca];B[ae];W[be];B[bd];W[ad]C[\u505a\u4e0d\u51fa\u7b2c\u4e8c\u96bb\u773c\u3002])))(;W[da]MN[4]N[\u767d\u4e0d\u884c];B[ba];W[ca];B[bb];W[ea];B[be]C[\u9ed1\u68cb\u6de8\u6d3b\u3002]))(;B[ba]MN[3]N[\u8b8a\u5316\u57162];W[cc](;B[bb];W[da];B[be]C[\u9019\u6a23\u9ed1\u68cb\u5012\u662f\u53ef\u4ee5\u505a\u6d3b\uff0c\u4f46\u767d6\u5148\u624b\u5403\u4e8c\u5b50\uff0c\u9ed1\u68cb\u640d\u5931\u5f88\u5927\u3002])(;B[da]MN[5]N[\u8b8a\u5316\u5716];W[bd];B[be];W[bb];B[ab]C[\u6210\u52ab\u3002])))(;W[be]MN[2]N[\u767d\u4e0d\u884c];B[ba];W[ab];B[bd]C[\u9ed1\u68cb\u6de8\u6d3b\u3002]))(;B[be]N[\u5931\u6557\u57162];W[bb];B[cc];W[da];B[ca];W[ea];B[cb];W[bc];B[ab];W[ba];B[ad];W[af](;B[ae];W[ac]C[\u6709\u773c\u6bba\u778e\u3002])(;B[ac]MN[13]C[\u60f3\u8981\u96d9\u6d3b]N[\u8b8a\u5316\u5716];W[ae]C[\u53ef\u662f\u6709\u65b7\u982d\uff0c\u8b8a\u6210\u6de8\u6b7b\u3002])))\n",
    "black_crucial_stone": "ce,db",
    "white_crucial_stone": "",
    "category": "TOLIVE",
    "winning_color": "b",
    "turn_color": "b",
    "date": "2020-04-16",
    "answer_firstmove": "bb",
    "mask_type": "automask",
    "distance2wall": 4,
    "mask_filename": "",
    "mask_sgf": "(;FF[4]CA[UTF-8]AP[GoGui:1.4.9]KM[6.5]DT[2020-03-25]AB[ap][bp][dp][cp][ep][eq][er][es][br][ar][bs]AW[cr][cs][bq])",
    "add_pieces_before_masked": "",
    "remove_pieces_before_masked": "",
    "add_pieces_after_masked": "",
    "remove_pieces_after_masked": "",
    "masked_sgf_str": "(;CA[UTF-8]GM[1]AP[StoneBase:SGFParser.3.0]SZ[19]HA[0]TARGET[TOLIVE-BLACK-&ce,db];B[cn];W[];B[co];W[];B[cp];W[];B[cq];W[];B[cr];W[];B[cs];W[];B[dn];W[];B[do];W[];B[dq];W[];B[dr];W[];B[ds];W[];B[en];W[];B[eo];W[];B[ep];W[];B[eq];W[];B[er];W[];B[es];W[];B[fn];W[];B[fo];W[];B[fq];W[];B[fr];W[];B[fs];W[];B[gn];W[];B[go];W[];B[gp];W[];B[gq];W[];B[gr];W[];B[gs];W[];B[hn];W[];B[ho];W[];B[hq];W[];B[hr];W[];B[hs];W[];B[in];W[];B[io];W[];B[ip];W[];B[iq];W[];B[ir];W[];B[is];W[];B[jn];W[];B[jo];W[];B[jq];W[];B[jr];W[];B[js];W[];B[kn];W[];B[ko];W[];B[kp];W[];B[kq];W[];B[kr];W[];B[ks];W[];B[ln];W[];B[lo];W[];B[lq];W[];B[lr];W[];B[ls];W[];B[mn];W[];B[mo];W[];B[mp];W[];B[mq];W[];B[mr];W[];B[ms];W[];B[na];W[];B[nb];W[];B[nc];W[];B[nd];W[];B[ne];W[];B[nf];W[];B[ng];W[];B[nh];W[];B[ni];W[];B[nj];W[];B[nk];W[];B[nl];W[];B[nm];W[];B[nn];W[];B[no];W[];B[nq];W[];B[nr];W[];B[ns];W[];B[oa];W[];B[ob];W[];B[oc];W[];B[od];W[];B[oe];W[];B[of];W[];B[og];W[];B[oh];W[];B[oi];W[];B[oj];W[];B[ok];W[];B[ol];W[];B[om];W[];B[on];W[];B[oo];W[];B[op];W[];B[oq];W[];B[or];W[];B[os];W[];B[pb];W[];B[pc];W[];B[pe];W[];B[pg];W[];B[pi];W[la];B[pk];W[lb];B[pm];W[lc];B[po];W[ld];B[pq];W[le];B[pr];W[lf];B[ps];W[lg];B[qa];W[lh];B[qb];W[li];B[qc];W[lj];B[qd];W[lk];B[qe];W[al];B[qf];W[bl];B[qg];W[cl];B[qh];W[dl];B[qi];W[el];B[qj];W[fl];B[qk];W[gl];B[ql];W[hl];B[qm];W[il];B[qn];W[jl];B[qo];W[kl];B[qp];W[ll];B[qq];W[am];B[qr];W[an];B[qs];W[ao];B[ra];W[aq];B[rb];W[ar];B[rc];W[bm];B[rd];W[bn];B[re];W[bo];B[rf];W[bp];B[rg];W[bq];B[rh];W[br];B[ri];W[bs];B[rj];W[cm];B[rk];W[dm];B[rl];W[em];B[rm];W[fm];B[rn];W[gm];B[ro];W[hm];B[rp];W[im];B[rq];W[jm];B[rr];W[km];B[rs];W[lm];B[sb];W[ma];B[sc];W[mb];B[sd];W[mc];B[se];W[md];B[sf];W[me];B[sg];W[mf];B[sh];W[mg];B[si];W[mh];B[sj];W[mi];B[sk];W[mj];B[sl];W[mk];B[sm];W[ml];B[sn];W[mm];B[so];W[bf];B[sp];W[cf];B[sq];W[df];B[sr];W[ch];B[ss];W[dd];B[dc];W[ed];B[db];W[ec];B[cd];W[eb];B[ce];W[hc])",
    "black_search_goal": "TOLIVE",
    "white_search_goal": "",
    "target_block": "ce,db",
    "white_ko_rule": "disallow_ko",
    "black_ko_rule": "disallow_ko"
}